yfiles_jupyter_graphs_for_kuzu/Yfiles_Kuzu_Graphs.py
yfiles_jupyter_graphs_for_kuzu/__init__.py
yfiles_jupyter_graphs_for_kuzu-1.1.1.dist-info/licenses/LICENSE.md
yfiles_jupyter_graphs_for_kuzu-1.1.1.dist-info/METADATA
yfiles_jupyter_graphs_for_kuzu-1.1.1.dist-info/WHEEL
yfiles_jupyter_graphs_for_kuzu-1.1.1.dist-info/top_level.txt
yfiles_jupyter_graphs_for_kuzu-1.1.1.dist-info/RECORD
