Metadata-Version: 2.4
Name: yfiles_jupyter_graphs_for_kuzu
Version: 1.1.1
Summary: A Kuzu graph visualization package that uses the yfiles-jupyter-graphs widget
Author-email: yWorks Support Team <yfileshtml@yworks.com>
License-Expression: MIT
Project-URL: License, https://github.com/yWorks/yfiles-jupyter-graphs-for-kuzu/blob/kuzu/LICENSE.md
Project-URL: Bug Tracker, https://github.com/yWorks/yfiles-jupyter-graphs-for-kuzu/issues
Project-URL: Documentation, https://github.com/yWorks/yfiles-jupyter-graphs-for-kuzu/
Project-URL: Repository, https://github.com/yWorks/yfiles-jupyter-graphs-for-kuzu.git
Classifier: Development Status :: 5 - Production/Stable
Classifier: Framework :: IPython
Classifier: Intended Audience :: Developers
Classifier: Intended Audience :: Science/Research
Classifier: Programming Language :: Python :: 3
Classifier: Operating System :: OS Independent
Classifier: Framework :: Jupyter
Classifier: Framework :: Jupyter :: JupyterLab
Classifier: Framework :: Jupyter :: JupyterLab :: 3
Classifier: Framework :: Jupyter :: JupyterLab :: Extensions
Classifier: Framework :: Jupyter :: JupyterLab :: Extensions :: Prebuilt
Requires-Python: >=3.8
License-File: LICENSE.md
Requires-Dist: yfiles_jupyter_graphs>=1.10.9
Dynamic: license-file
